codai/__init__.py
codai/bot.py
codai/hci.py
codai/repl.py
codai/utils.py
codai/bots/codai.py
codai/bots/map.py
codai/bots/refactor.py
codai/cli/__init__.py
codai/cli/common.py
codai/cli/dev.py
codai/cli/main.py
codai/flows/batch_edit.py
codai-0.4.3.dist-info/METADATA
codai-0.4.3.dist-info/WHEEL
codai-0.4.3.dist-info/entry_points.txt
codai-0.4.3.dist-info/RECORD
